Metadata-Version: 1.1
Name: LinkedListModule
Version: 0.0.1
Summary: This is a basic implementation of single linked lists in Python.
Home-page: UNKNOWN
Author: Abeer Rao
Author-email: abeerrao@icloud.com
License: MIT
Keywords: LinkedLists
Platform: UNKNOWN
Classifier: Development Status :: 5 - Production/Stable
Classifier: Intended Audience :: Education
Classifier: Operating System :: MacOS :: MacOS X
Classifier: License :: OSI Approved :: MIT License
Classifier: Programming Language :: Python :: 3
